{ "backgroundcolor":"#000000",
 "compressionlevel":-1,
 "height":32,
 "infinite":false,
 "layers":[
        {
         "compression":"zlib",
         "data":"eJztkUEKwCAMBPOO\/v8j\/Y83i+deKkjQJMZELRhYsK27s6QJANLR0c+Vp3zm7nj2KFm1dzPYeB+efGp24Hv\/f2524Cd0nsn34vbwcwePLj18TQfs17DLDCm\/1V\/LlnJb2RZ8qgMAn2vJx+cerxVf6x3h55zjXzeYfw94rfjXoKQZmR8W8sOnuEhS9oPUw9D6alyLnNoOanuguKHhC8S3yORQPu6+RK2MF+XDX6s=",
         "encoding":"base64",
         "height":32,
         "id":1,
         "name":"back",
         "opacity":0.5,
         "type":"tilelayer",
         "visible":true,
         "width":32,
         "x":0,
         "y":0
        }, 
        {
         "compression":"zlib",
         "data":"eJzt0bEJACAMRNGs5v6DOIAOYGMhhxFF1ML\/4LpcDGgGAAAA4Efx9QGfSjVhImlxfrTHZN+J5CY3u7N79A90ftTRnvLu8ObbXu+GHd6bBVzUZf8=",
         "encoding":"base64",
         "height":32,
         "id":2,
         "name":"front",
         "opacity":1,
         "type":"tilelayer",
         "visible":true,
         "width":32,
         "x":0,
         "y":0
        }, 
        {
         "color":"#5555ff",
         "draworder":"topdown",
         "id":3,
         "name":"mods",
         "objects":[
                {
                 "height":16,
                 "id":690,
                 "name":"",
                 "properties":[
                        {
                         "name":"back",
                         "type":"string",
                         "value":"bars"
                        }, 
                        {
                         "name":"colorVariant",
                         "type":"string",
                         "value":"8"
                        }],
                 "rotation":0,
                 "type":"",
                 "visible":true,
                 "width":128,
                 "x":32,
                 "y":200
                }, 
                {
                 "height":16,
                 "id":694,
                 "name":"",
                 "properties":[
                        {
                         "name":"back",
                         "type":"string",
                         "value":"slopedinsetpanel"
                        }, 
                        {
                         "name":"colorVariant",
                         "type":"string",
                         "value":"8"
                        }],
                 "rotation":0,
                 "type":"",
                 "visible":true,
                 "width":8,
                 "x":24,
                 "y":200
                }, 
                {
                 "height":16,
                 "id":701,
                 "name":"",
                 "properties":[
                        {
                         "name":"back",
                         "type":"string",
                         "value":"slopedinsetpanel"
                        }, 
                        {
                         "name":"colorVariant",
                         "type":"string",
                         "value":"8"
                        }],
                 "rotation":0,
                 "type":"",
                 "visible":true,
                 "width":8,
                 "x":160,
                 "y":200
                }, 
                {
                 "height":16,
                 "id":703,
                 "name":"",
                 "properties":[
                        {
                         "name":"back",
                         "type":"string",
                         "value":"bars"
                        }, 
                        {
                         "name":"colorVariant",
                         "type":"string",
                         "value":"8"
                        }],
                 "rotation":0,
                 "type":"",
                 "visible":true,
                 "width":72,
                 "x":168,
                 "y":200
                }, 
                {
                 "height":8,
                 "id":705,
                 "name":"",
                 "properties":[
                        {
                         "name":"back",
                         "type":"string",
                         "value":"slopedinsetpanel"
                        }, 
                        {
                         "name":"colorVariant",
                         "type":"string",
                         "value":"2"
                        }],
                 "rotation":0,
                 "type":"",
                 "visible":true,
                 "width":8,
                 "x":24,
                 "y":192
                }, 
                {
                 "height":8,
                 "id":706,
                 "name":"",
                 "properties":[
                        {
                         "name":"back",
                         "type":"string",
                         "value":"sandstoneblock"
                        }, 
                        {
                         "name":"colorVariant",
                         "type":"string",
                         "value":"2"
                        }, 
                        {
                         "name":"front",
                         "type":"string",
                         "value":"sandstoneblock"
                        }],
                 "rotation":0,
                 "type":"",
                 "visible":true,
                 "width":64,
                 "x":32,
                 "y":216
                }, 
                {
                 "height":8,
                 "id":708,
                 "name":"",
                 "properties":[
                        {
                         "name":"colorVariant",
                         "type":"string",
                         "value":"2"
                        }, 
                        {
                         "name":"material",
                         "type":"string",
                         "value":"sandstoneblock"
                        }, 
                        {
                         "name":"mod",
                         "type":"string",
                         "value":"grass"
                        }],
                 "rotation":0,
                 "type":"",
                 "visible":true,
                 "width":8,
                 "x":24,
                 "y":216
                }, 
                {
                 "height":8,
                 "id":709,
                 "name":"",
                 "properties":[
                        {
                         "name":"colorVariant",
                         "type":"string",
                         "value":"2"
                        }, 
                        {
                         "name":"material",
                         "type":"string",
                         "value":"sandstoneblock"
                        }, 
                        {
                         "name":"mod",
                         "type":"string",
                         "value":"grass"
                        }],
                 "rotation":0,
                 "type":"",
                 "visible":true,
                 "width":8,
                 "x":120,
                 "y":216
                }, 
                {
                 "height":8,
                 "id":711,
                 "name":"",
                 "properties":[
                        {
                         "name":"colorVariant",
                         "type":"string",
                         "value":"2"
                        }, 
                        {
                         "name":"material",
                         "type":"string",
                         "value":"sandstoneblock"
                        }, 
                        {
                         "name":"mod",
                         "type":"string",
                         "value":"grass"
                        }],
                 "rotation":0,
                 "type":"",
                 "visible":true,
                 "width":16,
                 "x":224,
                 "y":216
                }, 
                {
                 "height":8,
                 "id":712,
                 "name":"",
                 "properties":[
                        {
                         "name":"colorVariant",
                         "type":"string",
                         "value":"8"
                        }, 
                        {
                         "name":"layer",
                         "type":"string",
                         "value":"back"
                        }, 
                        {
                         "name":"material",
                         "type":"string",
                         "value":"bars"
                        }, 
                        {
                         "name":"mod",
                         "type":"string",
                         "value":"grass"
                        }],
                 "rotation":0,
                 "type":"",
                 "visible":true,
                 "width":16,
                 "x":72,
                 "y":200
                }, 
                {
                 "height":8,
                 "id":713,
                 "name":"",
                 "properties":[
                        {
                         "name":"colorVariant",
                         "type":"string",
                         "value":"8"
                        }, 
                        {
                         "name":"layer",
                         "type":"string",
                         "value":"back"
                        }, 
                        {
                         "name":"material",
                         "type":"string",
                         "value":"bars"
                        }, 
                        {
                         "name":"mod",
                         "type":"string",
                         "value":"grass"
                        }],
                 "rotation":0,
                 "type":"",
                 "visible":true,
                 "width":8,
                 "x":88,
                 "y":208
                }, 
                {
                 "height":8,
                 "id":714,
                 "name":"",
                 "properties":[
                        {
                         "name":"colorVariant",
                         "type":"string",
                         "value":"8"
                        }, 
                        {
                         "name":"layer",
                         "type":"string",
                         "value":"back"
                        }, 
                        {
                         "name":"material",
                         "type":"string",
                         "value":"bars"
                        }, 
                        {
                         "name":"mod",
                         "type":"string",
                         "value":"grass"
                        }],
                 "rotation":0,
                 "type":"",
                 "visible":true,
                 "width":16,
                 "x":120,
                 "y":208
                }, 
                {
                 "height":8,
                 "id":739,
                 "name":"",
                 "properties":[
                        {
                         "name":"colorVariant",
                         "type":"string",
                         "value":"8"
                        }, 
                        {
                         "name":"layer",
                         "type":"string",
                         "value":"back"
                        }, 
                        {
                         "name":"material",
                         "type":"string",
                         "value":"bars"
                        }, 
                        {
                         "name":"mod",
                         "type":"string",
                         "value":"grass"
                        }],
                 "rotation":0,
                 "type":"",
                 "visible":true,
                 "width":24,
                 "x":136,
                 "y":200
                }, 
                {
                 "height":8,
                 "id":740,
                 "name":"",
                 "properties":[
                        {
                         "name":"back",
                         "type":"string",
                         "value":"sandstoneblock"
                        }, 
                        {
                         "name":"colorVariant",
                         "type":"string",
                         "value":"2"
                        }, 
                        {
                         "name":"front",
                         "type":"string",
                         "value":"sandstoneblock"
                        }],
                 "rotation":0,
                 "type":"",
                 "visible":true,
                 "width":96,
                 "x":128,
                 "y":216
                }],
         "opacity":1,
         "type":"objectgroup",
         "visible":true,
         "x":0,
         "y":0
        }, 
        {
         "color":"#ff0000",
         "draworder":"topdown",
         "id":4,
         "name":"objects",
         "objects":[
                {
                 "gid":2147491445,
                 "height":160,
                 "id":680,
                 "name":"",
                 "rotation":0,
                 "type":"",
                 "visible":true,
                 "width":8,
                 "x":104,
                 "y":216
                }, 
                {
                 "gid":7812,
                 "height":20,
                 "id":681,
                 "name":"",
                 "rotation":0,
                 "type":"",
                 "visible":true,
                 "width":16,
                 "x":232,
                 "y":216
                }, 
                {
                 "gid":242,
                 "height":8,
                 "id":693,
                 "name":"",
                 "rotation":0,
                 "type":"",
                 "visible":true,
                 "width":8,
                 "x":8,
                 "y":216
                }, 
                {
                 "gid":6524,
                 "height":12,
                 "id":725,
                 "name":"",
                 "rotation":0,
                 "type":"",
                 "visible":true,
                 "width":8,
                 "x":24,
                 "y":192
                }, 
                {
                 "gid":6852,
                 "height":8,
                 "id":727,
                 "name":"",
                 "rotation":0,
                 "type":"",
                 "visible":true,
                 "width":8,
                 "x":160,
                 "y":208
                }, 
                {
                 "gid":7791,
                 "height":9,
                 "id":742,
                 "name":"",
                 "rotation":0,
                 "type":"",
                 "visible":true,
                 "width":64,
                 "x":24,
                 "y":216
                }, 
                {
                 "gid":7791,
                 "height":9,
                 "id":743,
                 "name":"",
                 "rotation":0,
                 "type":"",
                 "visible":true,
                 "width":64,
                 "x":168,
                 "y":216
                }, 
                {
                 "gid":9211,
                 "height":32,
                 "id":745,
                 "name":"",
                 "rotation":0,
                 "type":"",
                 "visible":true,
                 "width":16,
                 "x":88,
                 "y":216
                }, 
                {
                 "gid":9192,
                 "height":24,
                 "id":746,
                 "name":"",
                 "rotation":0,
                 "type":"",
                 "visible":true,
                 "width":48,
                 "x":112,
                 "y":216
                }],
         "opacity":1,
         "type":"objectgroup",
         "visible":true,
         "x":0,
         "y":0
        }, 
        {
         "color":"#ffff00",
         "draworder":"topdown",
         "id":5,
         "name":"wiring - lights & guns",
         "objects":[],
         "opacity":1,
         "type":"objectgroup",
         "visible":true,
         "x":0,
         "y":0
        }, 
        {
         "color":"#ff0000",
         "draworder":"topdown",
         "id":6,
         "name":"monsters & npcs",
         "objects":[],
         "opacity":1,
         "type":"objectgroup",
         "visible":true,
         "x":0,
         "y":0
        }, 
        {
         "color":"#00ffff",
         "draworder":"topdown",
         "id":7,
         "name":"wiring - locked door",
         "objects":[],
         "opacity":1,
         "type":"objectgroup",
         "visible":true,
         "x":0,
         "y":0
        }, 
        {
         "draworder":"topdown",
         "id":8,
         "name":"outside the map",
         "objects":[],
         "opacity":1,
         "type":"objectgroup",
         "visible":true,
         "x":0,
         "y":0
        }, 
        {
         "draworder":"topdown",
         "id":9,
         "name":"anchors etc",
         "objects":[
                {
                 "gid":251,
                 "height":8,
                 "id":683,
                 "name":"",
                 "rotation":0,
                 "type":"",
                 "visible":true,
                 "width":8,
                 "x":0,
                 "y":200
                }, 
                {
                 "gid":251,
                 "height":8,
                 "id":686,
                 "name":"",
                 "rotation":0,
                 "type":"",
                 "visible":true,
                 "width":8,
                 "x":248,
                 "y":200
                }, 
                {
                 "gid":240,
                 "height":8,
                 "id":687,
                 "name":"",
                 "rotation":0,
                 "type":"",
                 "visible":true,
                 "width":8,
                 "x":248,
                 "y":232
                }, 
                {
                 "gid":240,
                 "height":8,
                 "id":688,
                 "name":"",
                 "rotation":0,
                 "type":"",
                 "visible":true,
                 "width":8,
                 "x":0,
                 "y":232
                }, 
                {
                 "gid":238,
                 "height":8,
                 "id":689,
                 "name":"",
                 "rotation":0,
                 "type":"",
                 "visible":true,
                 "width":8,
                 "x":72,
                 "y":200
                }, 
                {
                 "height":168,
                 "id":692,
                 "name":"",
                 "properties":[
                        {
                         "name":"stagehand",
                         "type":"string",
                         "value":"objecttracker"
                        }],
                 "rotation":0,
                 "type":"",
                 "visible":true,
                 "width":224,
                 "x":24,
                 "y":56
                }],
         "opacity":1,
         "type":"objectgroup",
         "visible":true,
         "x":0,
         "y":0
        }, 
        {
         "draworder":"topdown",
         "id":10,
         "name":"items",
         "objects":[],
         "opacity":1,
         "type":"objectgroup",
         "visible":true,
         "x":0,
         "y":0
        }],
 "nextlayerid":11,
 "nextobjectid":749,
 "orientation":"orthogonal",
 "renderorder":"right-down",
 "tiledversion":"1.10.2",
 "tileheight":8,
 "tilesets":[
        {
         "firstgid":1,
         "source":"..\/..\/..\/tilesets\/packed\/materials.json"
        }, 
        {
         "firstgid":198,
         "source":"..\/..\/..\/tilesets\/packed\/supports.json"
        }, 
        {
         "firstgid":235,
         "source":"..\/..\/..\/tilesets\/packed\/miscellaneous.json"
        }, 
        {
         "firstgid":259,
         "source":"..\/..\/..\/tilesets\/packed\/liquids.json"
        }, 
        {
         "firstgid":287,
         "source":"..\/..\/..\/tilesets\/packed\/objects-by-race\/ancient.json"
        }, 
        {
         "firstgid":450,
         "source":"..\/..\/..\/tilesets\/packed\/objects-by-race\/apex.json"
        }, 
        {
         "firstgid":821,
         "source":"..\/..\/..\/tilesets\/packed\/objects-by-race\/avian.json"
        }, 
        {
         "firstgid":1126,
         "source":"..\/..\/..\/tilesets\/packed\/objects-by-race\/floran.json"
        }, 
        {
         "firstgid":1321,
         "source":"..\/..\/..\/tilesets\/packed\/objects-by-race\/generic.json"
        }, 
        {
         "firstgid":3305,
         "source":"..\/..\/..\/tilesets\/packed\/objects-by-race\/glitch.json"
        }, 
        {
         "firstgid":3531,
         "source":"..\/..\/..\/tilesets\/packed\/objects-by-race\/human.json"
        }, 
        {
         "firstgid":3819,
         "source":"..\/..\/..\/tilesets\/packed\/objects-by-race\/hylotl.json"
        }, 
        {
         "firstgid":4051,
         "source":"..\/..\/..\/tilesets\/packed\/objects-by-race\/novakid.json"
        }, 
        {
         "firstgid":4115,
         "source":"..\/..\/..\/tilesets\/packed\/objects-by-category\/breakable.json"
        }, 
        {
         "firstgid":4425,
         "source":"..\/..\/..\/tilesets\/packed\/objects-by-category\/decorative.json"
        }, 
        {
         "firstgid":5866,
         "source":"..\/..\/..\/tilesets\/packed\/objects-by-category\/door.json"
        }, 
        {
         "firstgid":5998,
         "source":"..\/..\/..\/tilesets\/packed\/objects-by-category\/farmable.json"
        }, 
        {
         "firstgid":6073,
         "source":"..\/..\/..\/tilesets\/packed\/objects-by-category\/furniture.json"
        }, 
        {
         "firstgid":6427,
         "source":"..\/..\/..\/tilesets\/packed\/objects-by-category\/light.json"
        }, 
        {
         "firstgid":6885,
         "source":"..\/..\/..\/tilesets\/packed\/objects-by-category\/railpoint.json"
        }, 
        {
         "firstgid":6890,
         "source":"..\/..\/..\/tilesets\/packed\/objects-by-category\/teleporter.json"
        }, 
        {
         "firstgid":6932,
         "source":"..\/..\/..\/tilesets\/packed\/objects-by-category\/trap.json"
        }, 
        {
         "firstgid":7136,
         "source":"..\/..\/..\/tilesets\/packed\/objects-by-category\/wire.json"
        }, 
        {
         "firstgid":7358,
         "source":"..\/..\/..\/tilesets\/packed\/objects-by-type\/container.json"
        }, 
        {
         "firstgid":7643,
         "source":"..\/..\/..\/tilesets\/packed\/objects-by-type\/teleporter.json"
        }, 
        {
         "firstgid":7670,
         "source":"..\/..\/..\/tilesets\/packed\/objects-by-race\/alta.json"
        }],
 "tilewidth":8,
 "type":"map",
 "version":"1.10",
 "width":32
}